arvi/HZ.py
arvi/__init__.py
arvi/ariadne_wrapper.py
arvi/berv.py
arvi/binning.py
arvi/config.py
arvi/dace_wrapper.py
arvi/exofop_wrapper.py
arvi/extra_data.py
arvi/gaia_wrapper.py
arvi/headers.py
arvi/instrument_specific.py
arvi/kepmodel_wrapper.py
arvi/kima_wrapper.py
arvi/lbl_wrapper.py
arvi/nasaexo_wrapper.py
arvi/plots.py
arvi/programs.py
arvi/reports.py
arvi/setup_logger.py
arvi/simbad_wrapper.py
arvi/sophie_wrapper.py
arvi/spectra.py
arvi/stats.py
arvi/stellar.py
arvi/timeseries.py
arvi/translations.py
arvi/utils.py
arvi/data/info.svg
arvi/data/obs_affected_ADC_issues.dat
arvi/data/obs_affected_blue_cryostat_issues.dat
arvi/data/extra/HD86226_PFS1.rdb
arvi/data/extra/HD86226_PFS2.rdb
arvi/data/extra/metadata.json
arvi-0.2.13.dist-info/licenses/LICENSE
arvi-0.2.13.dist-info/METADATA
arvi-0.2.13.dist-info/WHEEL
arvi-0.2.13.dist-info/top_level.txt
arvi-0.2.13.dist-info/RECORD
