Metadata-Version: 2.4
Name: arvi
Version: 0.2.13
Summary: The Automated RV Inspector
Author-email: João Faria <joao.faria@unige.ch>
License: MIT
Project-URL: Repository, https://github.com/j-faria/arvi
Keywords: RV,exoplanets
Classifier: Programming Language :: Python :: 3
Requires-Python: >=3.8
License-File: LICENSE
Requires-Dist: mock; python_version < "3.3"
Requires-Dist: numpy
Requires-Dist: scipy
Requires-Dist: matplotlib
Requires-Dist: astropy
Requires-Dist: dace-query
Requires-Dist: loguru
Requires-Dist: tqdm
Requires-Dist: pySWEETCat
Requires-Dist: kepmodel
Dynamic: license-file
